novncbot/__init__.py
novncbot/novncbot.py
novncbot-0.1.0.dist-info/LICENSE
novncbot-0.1.0.dist-info/METADATA
novncbot-0.1.0.dist-info/WHEEL
novncbot-0.1.0.dist-info/top_level.txt
novncbot-0.1.0.dist-info/RECORD
