Metadata-Version: 2.1
Name: novncbot
Version: 0.1.0
Summary: An asynchronous noVNC client
Home-page: https://github.com/shawrkbait/novncbot
Author: Shawn Johnson
Author-email: sjohnson@axiomega.com
License: UNKNOWN
Platform: UNKNOWN
Classifier: Programming Language :: Python :: 3
Classifier: Operating System :: OS Independent
Requires-Dist: selenium
